etlt/Transformer.py
etlt/__init__.py
etlt/cleaner/DateCleaner.py
etlt/cleaner/MoneyCleaner.py
etlt/cleaner/WhitespaceCleaner.py
etlt/cleaner/__init__.py
etlt/condition/AndCondition.py
etlt/condition/CompoundCondition.py
etlt/condition/Condition.py
etlt/condition/FalseCondition.py
etlt/condition/GlobCondition.py
etlt/condition/InListCondition.py
etlt/condition/OrCondition.py
etlt/condition/PlainCondition.py
etlt/condition/RegularExpressionCondition.py
etlt/condition/SimpleCondition.py
etlt/condition/SimpleConditionFactory.py
etlt/condition/TrueCondition.py
etlt/condition/__init__.py
etlt/dimension/RegularDimension.py
etlt/dimension/Type2ReferenceDimension.py
etlt/dimension/__init__.py
etlt/helper/Allen.py
etlt/helper/Type2CondenseHelper.py
etlt/helper/Type2Helper.py
etlt/helper/Type2JoinHelper.py
etlt/helper/__init__.py
etlt/reader/Reader.py
etlt/reader/UniversalCsvReader.py
etlt/reader/UniversalCsvReaderFormatHelper.py
etlt/reader/__init__.py
etlt/writer/SqlLoaderWriter.py
etlt/writer/Writer.py
etlt/writer/__init__.py
etlt-1.0.0.dist-info/LICENSE
etlt-1.0.0.dist-info/METADATA
etlt-1.0.0.dist-info/WHEEL
etlt-1.0.0.dist-info/RECORD
