Metadata-Version: 2.1
Name: ETLT
Version: 1.0.0
Summary: Extract Transform Load - but not in that strict order
Home-page: https://github.com/PyETLT/etlt
License: MIT
Keywords: ETLT,ETL,ELT,Extract,Transform,Load,DWH,Data,Warehouse
Author: Set Based IT Consultancy
Author-email: info@setbased.nl
Requires-Python: >=3.9.0,<4.0.0
Classifier: Development Status :: 5 - Production/Stable
Classifier: Environment :: Console
Classifier: Intended Audience :: Developers
Classifier: License :: OSI Approved :: MIT License
Classifier: Operating System :: OS Independent
Classifier: Programming Language :: Python :: 3
Classifier: Programming Language :: Python :: 3.9
Classifier: Programming Language :: Python :: 3.10
Classifier: Programming Language :: Python :: 3.11
Classifier: Programming Language :: Python :: 3.12
Classifier: Topic :: Database
Requires-Dist: chardet (>=5.2.0,<6.0.0)
Project-URL: Repository, https://github.com/PyETLT/etlt
